polsartools-0.10.dist-info/RECORD
polsartools-0.10.dist-info/WHEEL
polsartools-0.10.dist-info/entry_points.txt
polsartools-0.10.dist-info/top_level.txt
polsartools-0.10.dist-info/METADATA
polsartools-0.10.dist-info/licenses/LICENSE
polsartools/yam4cpp.cpython-313-darwin.so
polsartools/version.json
polsartools/__init__.py
polsartools/__version__.py
polsartools/rflee.cpython-313-darwin.so
polsartools/.gitignore
polsartools/cprvicpp.cpython-313-darwin.so
polsartools/sensors/isro_asar.py
polsartools/sensors/alos2.py
polsartools/sensors/s1grd_old.py
polsartools/sensors/isro_asar_old.py
polsartools/sensors/sentinel1.py
polsartools/sensors/nisar.py
polsartools/sensors/eos04.py
polsartools/sensors/__init__.py
polsartools/sensors/chyaan2.py
polsartools/sensors/basic_func.py
polsartools/sensors/uavsar.py
polsartools/sensors/risat.py
polsartools/sensors/.gitignore
polsartools/sensors/esar.py
polsartools/sensors/rs2_fp.py
polsartools/sensors/nisar_old.py
polsartools/sensors/alos1.py
polsartools/analysis/plot_h_theta_fp.py
polsartools/analysis/rgb_dp.py
polsartools/analysis/signature_fp.py
polsartools/analysis/plot_h_theta_cp.py
polsartools/analysis/__init__.py
polsartools/analysis/pauli_rgb.py
polsartools/analysis/rgb.py
polsartools/analysis/plot_h_alpha_dp.py
polsartools/analysis/plot_h_alpha_fp.py
polsartools/analysis/cluster_h_alpha_fp.py
polsartools/analysis/plot_h_a_alpha_fp.py
polsartools/polsar/__init__.py
polsartools/polsar/.gitignore
polsartools/polsar/dxp/dp_desc.py
polsartools/polsar/dxp/dprsic.py
polsartools/polsar/dxp/prvi_dp.py
polsartools/polsar/dxp/powers_dp.py
polsartools/polsar/dxp/dxp_infiles.py
polsartools/polsar/dxp/rvi_dp.py
polsartools/polsar/dxp/__init__.py
polsartools/polsar/dxp/post_proc_eg.py
polsartools/polsar/dxp/dprbic.py
polsartools/polsar/dxp/dprsi.py
polsartools/polsar/dxp/dprvi.py
polsartools/polsar/dxp/dprvic.py
polsartools/polsar/dxp/dop_dp.py
polsartools/polsar/dxp/dprbi.py
polsartools/polsar/dxp/powers_dp_grd.py
polsartools/polsar/dxp/shannon_h_dp.py
polsartools/polsar/dxp/h_alpha_dp.py
polsartools/polsar/dcp/__init__.py
polsartools/polsar/dcp/mf3cd.py
polsartools/polsar/dcp/dcp_infiles.py
