Metadata-Version: 2.1
Name: polsartools
Version: 0.10
Summary: A python package for processing Polarimetric Synthetic Aperture Radar (PolSAR) data.
Home-page: https://github.com/polsartools/polsartools
Author: Narayanarao Bhogapurapu
Author-email: bnarayanarao@nitw.ac.in
Classifier: Programming Language :: Python :: 3
Classifier: Operating System :: OS Independent
Requires-Python: >=3.6
License-File: LICENSE
Requires-Dist: numpy
Requires-Dist: gdal
Requires-Dist: scipy
Requires-Dist: click
Requires-Dist: tqdm
Requires-Dist: matplotlib
Requires-Dist: pybind11
Requires-Dist: tables
Requires-Dist: netcdf4
Requires-Dist: scikit-image
Provides-Extra: dev
Requires-Dist: pytest; extra == "dev"
Requires-Dist: sphinx; extra == "dev"
Requires-Dist: pydata-sphinx-theme; extra == "dev"
